timecube/__init__.py
timecube/timecube.py
timecube-1.1.1.dist-info/LICENSE
timecube-1.1.1.dist-info/METADATA
timecube-1.1.1.dist-info/WHEEL
timecube-1.1.1.dist-info/top_level.txt
timecube-1.1.1.dist-info/RECORD
