Metadata-Version: 2.1
Name: timecube
Version: 1.1.1
Summary: When you need to fill up space with something more interesting than Lorem Ipsum
Home-page: https://github.com/FullstackSoftwareInnovations/timecube-py/
Author: Fullstack Software Innovations
Author-email: chris@fullstack.software
License: UNKNOWN
Platform: UNKNOWN
Classifier: Programming Language :: Python :: 3
Classifier: License :: OSI Approved :: MIT License
Classifier: Operating System :: OS Independent
Requires-Python: >=3.6
License-File: LICENSE
